README.rst
setup.cfg
setup.py
src/tabular_dataset/__init__.py
src/tabular_dataset/tabular_dataset.py
src/tabular_dataset.egg-info/PKG-INFO
src/tabular_dataset.egg-info/SOURCES.txt
src/tabular_dataset.egg-info/dependency_links.txt
src/tabular_dataset.egg-info/not-zip-safe
src/tabular_dataset.egg-info/requires.txt
src/tabular_dataset.egg-info/top_level.txt
test/test_tabular_dataset.py