Metadata-Version: 1.1
Name: tabular-dataset
Version: 0.0.1
Summary: Simple tabular dataset manipulation
Home-page: https://github.com/voglster/tabular_dataset
Author: James Vogel
Author-email: jim.m.vogel@gmail.com
License: GPLv3
Platform: UNKNOWN
Classifier: Intended Audience :: Developers
Classifier: Operating System :: Unix
Classifier: Operating System :: POSIX
Classifier: Operating System :: Microsoft :: Windows
Classifier: Programming Language :: Python
Classifier: Programming Language :: Python :: 3.6
Classifier: Topic :: Utilities
